{
  "version": 1,
  "updated_at_utc": "2026-01-19T14:16:20.402984+00:00",
  "signals": {
    "HYPE/USDC:USDC|e8db4ab6fde8": {
      "signal_id": "e8db4ab6fde8",
      "symbol": "HYPE/USDC:USDC",
      "created_at_utc": "2025-12-16T07:26:13.914483+00:00",
      "last_seen_utc": "2025-12-16T08:26:14.587556+00:00",
      "actions_sent": {
        "WATCH": {
          "sent_at_utc": "2025-12-16T08:26:14.587556+00:00",
          "expires_at_utc": "2025-12-16T09:26:14.587556+00:00",
          "hash": "db1991a01037327c4d5a30c2db4e978c87aa60f3"
        }
      }
    },
    "HYPE/USDC:USDC|c4d8378823d9": {
      "signal_id": "c4d8378823d9",
      "symbol": "HYPE/USDC:USDC",
      "created_at_utc": "2025-12-22T00:31:13.381324+00:00",
      "last_seen_utc": "2025-12-22T00:56:13.252111+00:00",
      "actions_sent": {
        "EXECUTE_NOW": {
          "sent_at_utc": "2025-12-22T00:31:13.381324+00:00",
          "expires_at_utc": "2025-12-22T01:01:13.381324+00:00",
          "hash": "34996e1fb02ad2b34cc9c2db0aabb1dd326c1b69"
        }
      }
    },
    "HYPE/USDC:USDC|337bb97bcc13": {
      "signal_id": "337bb97bcc13",
      "symbol": "HYPE/USDC:USDC",
      "created_at_utc": "2025-12-25T00:31:11.394067+00:00",
      "last_seen_utc": "2025-12-25T00:41:13.835779+00:00",
      "actions_sent": {
        "EXECUTE_NOW": {
          "sent_at_utc": "2025-12-25T00:31:11.394067+00:00",
          "expires_at_utc": "2025-12-25T01:01:11.394067+00:00",
          "hash": "fbbff979c660c57485b6269265fb40a80d9fcf98"
        }
      }
    },
    "HYPE/USDC:USDC|7093c341f165": {
      "signal_id": "7093c341f165",
      "symbol": "HYPE/USDC:USDC",
      "created_at_utc": "2025-12-25T19:31:13.125828+00:00",
      "last_seen_utc": "2025-12-25T19:56:16.107064+00:00",
      "actions_sent": {
        "EXECUTE_NOW": {
          "sent_at_utc": "2025-12-25T19:31:13.125828+00:00",
          "expires_at_utc": "2025-12-25T20:01:13.125828+00:00",
          "hash": "d73a90e024f3d1b955445e3c1e7e806bc08a591c"
        }
      }
    },
    "HYPE/USDC:USDC|e94fb50a5b45": {
      "signal_id": "e94fb50a5b45",
      "symbol": "HYPE/USDC:USDC",
      "created_at_utc": "2025-12-26T07:31:16.104087+00:00",
      "last_seen_utc": "2025-12-26T07:41:13.617257+00:00",
      "actions_sent": {
        "EXECUTE_NOW": {
          "sent_at_utc": "2025-12-26T07:31:16.104087+00:00",
          "expires_at_utc": "2025-12-26T08:01:16.104087+00:00",
          "hash": "b0bac805221dce19c26c0a69b7108f59d9aff40a"
        }
      }
    },
    "HYPE/USDC:USDC|ea9c717da43b": {
      "signal_id": "ea9c717da43b",
      "symbol": "HYPE/USDC:USDC",
      "created_at_utc": "2026-01-01T21:06:14.764162+00:00",
      "last_seen_utc": "2026-01-01T21:31:11.200062+00:00",
      "actions_sent": {
        "EXECUTE_NOW": {
          "sent_at_utc": "2026-01-01T21:06:14.764162+00:00",
          "expires_at_utc": "2026-01-01T21:36:14.764162+00:00",
          "hash": "91473918501ce8e9dd85e4f956035fc4dc90550b"
        }
      }
    },
    "HYPE/USDC:USDC|63643f24ea4f": {
      "signal_id": "63643f24ea4f",
      "symbol": "HYPE/USDC:USDC",
      "created_at_utc": "2026-01-09T01:31:15.942242+00:00",
      "last_seen_utc": "2026-01-09T01:41:14.502602+00:00",
      "actions_sent": {
        "EXECUTE_NOW": {
          "sent_at_utc": "2026-01-09T01:31:15.942242+00:00",
          "expires_at_utc": "2026-01-09T02:01:15.942242+00:00",
          "hash": "6a4794bba329792d77dadbe9485655a75b7d4d74"
        }
      }
    },
    "HYPE/USDC:USDC|067afe5fa46b": {
      "signal_id": "067afe5fa46b",
      "symbol": "HYPE/USDC:USDC",
      "created_at_utc": "2026-01-09T02:16:17.331483+00:00",
      "last_seen_utc": "2026-01-09T02:56:17.027596+00:00",
      "actions_sent": {
        "EXECUTE_NOW": {
          "sent_at_utc": "2026-01-09T02:51:16.532340+00:00",
          "expires_at_utc": "2026-01-09T03:21:16.532340+00:00",
          "hash": "f5c9d9a5ae708fcfdf142f4621ae445fec1da22b"
        }
      }
    },
    "HYPE/USDC:USDC|20314bd143ec": {
      "signal_id": "20314bd143ec",
      "symbol": "HYPE/USDC:USDC",
      "created_at_utc": "2026-01-09T11:16:15.953220+00:00",
      "last_seen_utc": "2026-01-09T11:56:13.453071+00:00",
      "actions_sent": {
        "EXECUTE_NOW": {
          "sent_at_utc": "2026-01-09T11:46:17.925776+00:00",
          "expires_at_utc": "2026-01-09T12:16:17.925776+00:00",
          "hash": "6850fb543acf6da6e1a49904507624b55f5f79af"
        }
      }
    },
    "HYPE/USDC:USDC|e0fd11ae424c": {
      "signal_id": "e0fd11ae424c",
      "symbol": "HYPE/USDC:USDC",
      "created_at_utc": "2026-01-09T20:16:15.302552+00:00",
      "last_seen_utc": "2026-01-09T20:26:29.763054+00:00",
      "actions_sent": {
        "EXECUTE_NOW": {
          "sent_at_utc": "2026-01-09T20:16:15.302552+00:00",
          "expires_at_utc": "2026-01-09T20:46:15.302552+00:00",
          "hash": "97243e579de588d9d7efcf516408e8c6f23a2037"
        }
      }
    },
    "HYPE/USDC:USDC|2d9e7fc923f0": {
      "signal_id": "2d9e7fc923f0",
      "symbol": "HYPE/USDC:USDC",
      "created_at_utc": "2026-01-09T21:31:20.930176+00:00",
      "last_seen_utc": "2026-01-09T21:56:15.290282+00:00",
      "actions_sent": {
        "EXECUTE_NOW": {
          "sent_at_utc": "2026-01-09T21:31:20.930176+00:00",
          "expires_at_utc": "2026-01-09T22:01:20.930176+00:00",
          "hash": "ed6682f0cb1e0e16dff5207c3ca145e3aeabc730"
        }
      }
    },
    "HYPE/USDC:USDC|7291f47f75e3": {
      "signal_id": "7291f47f75e3",
      "symbol": "HYPE/USDC:USDC",
      "created_at_utc": "2026-01-10T09:16:16.195680+00:00",
      "last_seen_utc": "2026-01-10T09:36:15.821909+00:00",
      "actions_sent": {
        "EXECUTE_NOW": {
          "sent_at_utc": "2026-01-10T09:16:16.195680+00:00",
          "expires_at_utc": "2026-01-10T09:46:16.195680+00:00",
          "hash": "eb11b8c3f5a005bd80baacc11c31ae23639b9f14"
        }
      }
    },
    "HYPE/USDC:USDC|afca4d449f57": {
      "signal_id": "afca4d449f57",
      "symbol": "HYPE/USDC:USDC",
      "created_at_utc": "2026-01-15T19:46:26.231093+00:00",
      "last_seen_utc": "2026-01-15T19:56:23.443390+00:00",
      "actions_sent": {
        "EXECUTE_NOW": {
          "sent_at_utc": "2026-01-15T19:46:26.231093+00:00",
          "expires_at_utc": "2026-01-15T20:16:26.231093+00:00",
          "hash": "a113d4e254683d69c1364d984194bd43a440d5f4"
        }
      }
    },
    "HYPE/USDC:USDC|cea39493e24f": {
      "signal_id": "cea39493e24f",
      "symbol": "HYPE/USDC:USDC",
      "created_at_utc": "2026-01-15T21:56:16.453439+00:00",
      "last_seen_utc": "2026-01-15T21:56:16.453439+00:00",
      "actions_sent": {
        "EXECUTE_NOW": {
          "sent_at_utc": "2026-01-15T21:56:16.453439+00:00",
          "expires_at_utc": "2026-01-15T22:26:16.453439+00:00",
          "hash": "35c7395db6f40e9e152e02ca8ce2c16772779f74"
        }
      }
    },
    "HYPE/USDC:USDC|8bcce8c56050": {
      "signal_id": "8bcce8c56050",
      "symbol": "HYPE/USDC:USDC",
      "created_at_utc": "2026-01-18T22:31:20.707149+00:00",
      "last_seen_utc": "2026-01-18T22:56:15.885664+00:00",
      "actions_sent": {
        "EXECUTE_NOW": {
          "sent_at_utc": "2026-01-18T22:31:20.707149+00:00",
          "expires_at_utc": "2026-01-18T23:01:20.707149+00:00",
          "hash": "f1f2527e4fda4c4a861734f2ad8d32000d429902"
        }
      }
    },
    "HYPE/USDC:USDC|31cd61378a6b": {
      "signal_id": "31cd61378a6b",
      "symbol": "HYPE/USDC:USDC",
      "created_at_utc": "2026-01-19T08:46:21.838411+00:00",
      "last_seen_utc": "2026-01-19T08:56:20.092716+00:00",
      "actions_sent": {
        "EXECUTE_NOW": {
          "sent_at_utc": "2026-01-19T08:46:21.838411+00:00",
          "expires_at_utc": "2026-01-19T09:16:21.838411+00:00",
          "hash": "f2878fca8728d73e14414d4324fa9b4922f3fc1a"
        }
      }
    },
    "HYPE/USDC:USDC|d4e8d3330adf": {
      "signal_id": "d4e8d3330adf",
      "symbol": "HYPE/USDC:USDC",
      "created_at_utc": "2026-01-19T12:01:19.496322+00:00",
      "last_seen_utc": "2026-01-19T12:01:19.496322+00:00",
      "actions_sent": {
        "EXECUTE_NOW": {
          "sent_at_utc": "2026-01-19T12:01:19.496322+00:00",
          "expires_at_utc": "2026-01-19T12:31:19.496322+00:00",
          "hash": "448049f240f385143efc67e3212fbaaff6e3d841"
        }
      }
    },
    "HYPE/USDC:USDC|ccfb0bdee37b": {
      "signal_id": "ccfb0bdee37b",
      "symbol": "HYPE/USDC:USDC",
      "created_at_utc": "2026-01-19T12:21:19.201065+00:00",
      "last_seen_utc": "2026-01-19T12:26:24.338303+00:00",
      "actions_sent": {
        "EXECUTE_NOW": {
          "sent_at_utc": "2026-01-19T12:21:19.201065+00:00",
          "expires_at_utc": "2026-01-19T12:51:19.201065+00:00",
          "hash": "a45836a018a3a4b3a12a77ccd61be600f599b89f"
        }
      }
    },
    "HYPE/USDC:USDC|300cff540406": {
      "signal_id": "300cff540406",
      "symbol": "HYPE/USDC:USDC",
      "created_at_utc": "2026-01-19T12:31:18.883537+00:00",
      "last_seen_utc": "2026-01-19T12:41:22.231007+00:00",
      "actions_sent": {
        "EXECUTE_NOW": {
          "sent_at_utc": "2026-01-19T12:31:18.883537+00:00",
          "expires_at_utc": "2026-01-19T13:01:18.883537+00:00",
          "hash": "c8478b4c31ccd527ebc7efd40005cb110fbda56c"
        }
      }
    },
    "HYPE/USDC:USDC|61a4f8a4b3d5": {
      "signal_id": "61a4f8a4b3d5",
      "symbol": "HYPE/USDC:USDC",
      "created_at_utc": "2026-01-19T12:46:19.909983+00:00",
      "last_seen_utc": "2026-01-19T12:56:20.522088+00:00",
      "actions_sent": {
        "EXECUTE_NOW": {
          "sent_at_utc": "2026-01-19T12:46:19.909983+00:00",
          "expires_at_utc": "2026-01-19T13:16:19.909983+00:00",
          "hash": "c32c089c3f77546cbcebc41cf0930156c37e501f"
        }
      }
    },
    "HYPE/USDC:USDC|d9f60dbae864": {
      "signal_id": "d9f60dbae864",
      "symbol": "HYPE/USDC:USDC",
      "created_at_utc": "2026-01-19T13:01:21.117952+00:00",
      "last_seen_utc": "2026-01-19T13:11:24.597516+00:00",
      "actions_sent": {
        "EXECUTE_NOW": {
          "sent_at_utc": "2026-01-19T13:01:21.117952+00:00",
          "expires_at_utc": "2026-01-19T13:31:21.117952+00:00",
          "hash": "88e28929c63969bee9aef46d3022d341168ccfff"
        }
      }
    },
    "HYPE/USDC:USDC|cec289657a33": {
      "signal_id": "cec289657a33",
      "symbol": "HYPE/USDC:USDC",
      "created_at_utc": "2026-01-19T13:16:19.245053+00:00",
      "last_seen_utc": "2026-01-19T13:26:31.166053+00:00",
      "actions_sent": {
        "EXECUTE_NOW": {
          "sent_at_utc": "2026-01-19T13:16:19.245053+00:00",
          "expires_at_utc": "2026-01-19T13:46:19.245053+00:00",
          "hash": "959110998a2e882145c379aad3f2c9a02be2d3eb"
        }
      }
    },
    "HYPE/USDC:USDC|2ee5613dd290": {
      "signal_id": "2ee5613dd290",
      "symbol": "HYPE/USDC:USDC",
      "created_at_utc": "2026-01-19T13:31:20.228601+00:00",
      "last_seen_utc": "2026-01-19T13:41:18.347727+00:00",
      "actions_sent": {
        "EXECUTE_NOW": {
          "sent_at_utc": "2026-01-19T13:31:20.228601+00:00",
          "expires_at_utc": "2026-01-19T14:01:20.228601+00:00",
          "hash": "d2ac48cac5317b183db1ac51f31d6552f6bb4434"
        }
      }
    },
    "HYPE/USDC:USDC|2c9ca86fea94": {
      "signal_id": "2c9ca86fea94",
      "symbol": "HYPE/USDC:USDC",
      "created_at_utc": "2026-01-19T13:46:22.117250+00:00",
      "last_seen_utc": "2026-01-19T13:56:22.912560+00:00",
      "actions_sent": {
        "EXECUTE_NOW": {
          "sent_at_utc": "2026-01-19T13:46:22.117250+00:00",
          "expires_at_utc": "2026-01-19T14:16:22.117250+00:00",
          "hash": "6da95d68774395a5f482889e2a90ba7a86be77e0"
        }
      }
    },
    "HYPE/USDC:USDC|5b6d5240e41d": {
      "signal_id": "5b6d5240e41d",
      "symbol": "HYPE/USDC:USDC",
      "created_at_utc": "2026-01-19T14:01:22.396050+00:00",
      "last_seen_utc": "2026-01-19T14:11:21.986003+00:00",
      "actions_sent": {
        "EXECUTE_NOW": {
          "sent_at_utc": "2026-01-19T14:01:22.396050+00:00",
          "expires_at_utc": "2026-01-19T14:31:22.396050+00:00",
          "hash": "5406a80c6be4dd917fec9953f48ecb1bdd663098"
        }
      }
    },
    "HYPE/USDC:USDC|228eaa46b655": {
      "signal_id": "228eaa46b655",
      "symbol": "HYPE/USDC:USDC",
      "created_at_utc": "2026-01-19T14:16:19.707210+00:00",
      "last_seen_utc": "2026-01-19T14:16:19.707210+00:00",
      "actions_sent": {
        "EXECUTE_NOW": {
          "sent_at_utc": "2026-01-19T14:16:19.707210+00:00",
          "expires_at_utc": "2026-01-19T14:46:19.707210+00:00",
          "hash": "927bb3edccd70e6bfa9f2af5a24d365e25241d43"
        }
      }
    }
  },
  "rolling_state": {
    "candidate": "trending",
    "dir": "down",
    "streak": 16,
    "last_ts": "2026-01-19T14:15:45.848091+00:00"
  }
}